alg3dpy/__init__.py
alg3dpy/angles.py
alg3dpy/areas.py
alg3dpy/constants.py
alg3dpy/distances.py
alg3dpy/intersections.py
alg3dpy/line.py
alg3dpy/plane.py
alg3dpy/point.py
alg3dpy/vector.py
alg3dpy-0.18.1.dist-info/LICENSE
alg3dpy-0.18.1.dist-info/METADATA
alg3dpy-0.18.1.dist-info/WHEEL
alg3dpy-0.18.1.dist-info/top_level.txt
alg3dpy-0.18.1.dist-info/RECORD
