Metadata-Version: 2.1
Name: alg3dpy
Version: 0.18.1
Summary: 3D Algebra in Python
Home-page: https://github.com/saullocastro/alg3dpy
Author: Saullo G. P. Castro
Author-email: S.G.P.Castro@tudelft.nl
License: BSD
Keywords: algebra 3D mathematics geometry
Platform: UNKNOWN
Classifier: Development Status :: 4 - Beta
Classifier: Intended Audience :: Science/Research
Classifier: Intended Audience :: Education
Classifier: Topic :: Scientific/Engineering
Classifier: Topic :: Education
Classifier: Topic :: Software Development :: Libraries :: Python Modules
Classifier: Operating System :: POSIX :: BSD
Classifier: Operating System :: Microsoft :: Windows
Classifier: Operating System :: Unix
Classifier: Programming Language :: Python :: 3.6
Classifier: Programming Language :: Python :: 3.7
Classifier: Programming Language :: Python :: 3.8
Classifier: Programming Language :: Python :: 3.9
Classifier: License :: OSI Approved :: BSD License
License-File: LICENSE
Requires-Dist: numpy
